nlpashto/__init__.py
nlpashto/dataset_utils.py
nlpashto/pashto.py
nlpashto/pos_tagging.py
nlpashto/sentiment_analysis.py
nlpashto/tokenization.py
nlpashto/utils.py
nlpashto/word_segmentation.py
nlpashto-0.0.25.dist-info/LICENSE
nlpashto-0.0.25.dist-info/METADATA
nlpashto-0.0.25.dist-info/WHEEL
nlpashto-0.0.25.dist-info/top_level.txt
nlpashto-0.0.25.dist-info/RECORD
