Metadata-Version: 2.2
Name: nlpashto
Version: 0.0.25
Summary: Pashto Natural Language Processing Toolkit
Author-email: Ijazul Haq <ijazse@hotmail.com>
Project-URL: Homepage, https://github.com/dr-ijaz/nlpashto
Keywords: NLP,Pashto,NLPashto,Pashto NLP,NLP Toolkit,Word Segmentation,Tokenization,POS Tagging,Sentiment Analysis,Text Classification,Token Classification,Sequence Tagging,Text Cleaning
Classifier: Programming Language :: Python :: 3
Classifier: License :: OSI Approved :: MIT License
Classifier: Operating System :: OS Independent
Requires-Python: >=3.8
License-File: LICENSE
Requires-Dist: transformers
Requires-Dist: sklearn-crfsuite
Requires-Dist: emoji
Requires-Dist: joblib
Requires-Dist: numpy
Requires-Dist: pandas
Requires-Dist: requests
